watermarkipy/__init__.py
watermarkipy/watermark.py
watermarkipy-0.0.2.dist-info/LICENSE
watermarkipy-0.0.2.dist-info/METADATA
watermarkipy-0.0.2.dist-info/WHEEL
watermarkipy-0.0.2.dist-info/top_level.txt
watermarkipy-0.0.2.dist-info/RECORD
