Metadata-Version: 2.1
Name: watermarkipy
Version: 0.0.2
Author-email: George Tian <me@georgetian.com>
Maintainer-email: George Tian <me@georgetian.com>
License: MIT License
Project-URL: Homepage, https://github.com/georgetian3/watermarkipy
Project-URL: Bug Reports, https://github.com/georgetian3/watermarkipy/issues
Project-URL: Source, https://github.com/georgetian3/watermarkipy
Classifier: License :: OSI Approved :: MIT License
Classifier: Programming Language :: Python
Classifier: Programming Language :: Python :: 3
Requires-Python: >=3.9
License-File: LICENSE
Requires-Dist: pillow>=11.1.0
